torchret/__init__.py
torchret/model.py
torchret/utils.py
torchret-0.1.2.dist-info/METADATA
torchret-0.1.2.dist-info/WHEEL
torchret-0.1.2.dist-info/top_level.txt
torchret-0.1.2.dist-info/RECORD
